mangoplateapi/__init__.py
mangoplateapi/config.py
mangoplateapi/types.py
mangoplateapi/utils.py
mangoplateapi/mixins/__init__.py
mangoplateapi/mixins/code.py
mangoplateapi/mixins/keyword.py
mangoplateapi/mixins/restaurant.py
mangoplateapi/mixins/review.py
mangoplateapi/mixins/story.py
mangoplateapi/mixins/theme.py
mangoplateapi-1.0.16.dist-info/METADATA
mangoplateapi-1.0.16.dist-info/WHEEL
mangoplateapi-1.0.16.dist-info/top_level.txt
mangoplateapi-1.0.16.dist-info/RECORD
