Metadata-Version: 2.1
Name: mangoplateapi
Version: 1.0.16
Summary: Fast and effective Mangoplate Private API wrapper
Author: 8ㅁ8
License: MIT
Keywords: mangoplate api
Classifier: Development Status :: 4 - Beta
Classifier: Intended Audience :: Developers
Classifier: License :: OSI Approved :: MIT License
Classifier: Topic :: Software Development :: Libraries :: Python Modules
Classifier: Programming Language :: Python :: 3.7
Classifier: Programming Language :: Python :: 3.8
Classifier: Programming Language :: Python :: 3.9
Requires-Python: >=3.7
Requires-Dist: requests <3.0,>=2.25.1
